LICENSE
README.md
setup.cfg
setup.py
padtest/__init__.py
padtest.egg-info/PKG-INFO
padtest.egg-info/SOURCES.txt
padtest.egg-info/dependency_links.txt
padtest.egg-info/requires.txt
padtest.egg-info/top_level.txt
padtest/geometry/__init__.py
padtest/geometry/geometry.py
padtest/geometry/interface.py
padtest/geometry/plate.py
padtest/geometry/polygon.py
padtest/geometry/solid.py
padtest/material/__init__.py
padtest/material/plate.py
padtest/material/soil.py
padtest/model/__init__.py
padtest/model/model.py
padtest/model/plate.py
padtest/model/solid.py